[
  {
    "value": "Puntos_0",
    "synonyms": [
      "Puntos_0",
      "ninún día",
      "nunca",
      "muy pocas veces",
      "jamás",
      "nunca jamás",
      "muy poca",
      "muy pocas",
      "casi nunca",
      "ninguna vez",
      "en ninguna ocasión",
      "ningún día",
      "en ningún momento",
      "prácticamente nunca",
      "una vez",
      "ningún",
      "para nada",
      "muy poca frecuencia",
      "muy poco",
      "no me pasa",
      "nada",
      "pocas veces",
      "poco",
      "siempre tengo interés",
      "tengo mucho interés",
      "me interesan las cosas",
      "duermo bien",
      "duermo muy bien",
      "no tengo problemas con el sueño",
      "no tengo problemas",
      "no suelo tener problemas",
      "no tengo ninguna dificultad",
      "no tengo ningún problema",
      "no suelo tener dificultades",
      "me llevo muy bien",
      "lo llevo muy bien",
      "llevo muy bien",
      "ni un día",
      "ni un solo día",
      "nunca estoy lento",
      "nunca me muevo lento",
      "nunca me muevo lentamente",
      "nunca estoy inquieto",
      "nunca estoy agitado",
      "nunca estoy nervioso",
      "nunca estoy lenta",
      "nunca me muevo lenta",
      "nunca estoy inquieta",
      "nunca estoy agitada",
      "nunca estoy nerviosa",
      "nunca he pensado en matarme",
      "nunca he pensado en sucidarme",
      "nunca he pensado en hacerme daño",
      "nunca he pensado en quitarme la vida",
      "no he pensado en matarme",
      "no he pensado en sucidarme",
      "no he pensado en hacerme daño",
      "no he pensado en quitarme la vida",
      "siempre tengo esperanza",
      "siempre tengo esperanzas",
      "no recuerdo",
      "no recuerdo ninguna",
      "no recuerdo ningún",
      "no me acuerdo"
    ]
  },
  {
    "value": "Puntos_1",
    "synonyms": [
      "Puntos_1",
      "varios días",
      "algunos días",
      "en ocasiones",
      "de vez en cuando",
      "alguna que otra vez",
      "alguna vez que otra",
      "a veces",
      "par de días",
      "varias veces",
      "algunas veces",
      "depende",
      "unos días",
      "hay cosas que sí",
      "hay días que sí",
      "a veces estoy cansado",
      "a veces me falta la energía",
      "tengo algunos problemas",
      "tengo algunas dificultades",
      "me llevo bien",
      "lo llevo bien",
      "llevo bien",
      "en varias ocasiones",
      "dos días",
      "tres días",
      "cuatro días",
      "cinco días",
      "seis días",
      "siete días",
      "2 días",
      "3 días",
      "4 días",
      "5 días",
      "6 días",
      "7 días",
      "de vez en cuando estoy lento",
      "de vez en cuando me muevo lento",
      "de vez en cuando me muevo lentamente",
      "de vez en cuando estoy inquieto",
      "de vez en cuando estoy agitado",
      "de vez en cuando estoy nervioso",
      "de vez en cuando estoy lenta",
      "de vez en cuando me muevo lenta",
      "de vez en cuando estoy inquieta",
      "de vez en cuando estoy agitada",
      "de vez en cuando estoy nerviosa",
      "a veces pienso en matarme",
      "a veces pienso en sucidarme",
      "a veces pienso en hacerme daño",
      "a veces pienso en quitarme la vida",
      "a veces pienso en cortarme las venas",
      "a veces pienso en tirarme por la ventana",
      "a veces pienso en tirarme de un puente",
      "hay cosas que sí me dan placer",
      "hay cosas que sí me interesan",
      "a veces me interesan algunas cosas",
      "a ratos",
      "alguna",
      "algunas",
      "algunos"
    ]
  },
  {
    "value": "Puntos_2",
    "synonyms": [
      "Puntos_2",
      "más de la mitad de los días",
      "bastantes veces",
      "bastantes ocasiones",
      "a menudo",
      "bastante",
      "bastante frecuencia",
      "abundantemente",
      "abundancia",
      "con frecuencia",
      "bastantes días",
      "un día sí otro no",
      "cada dos días",
      "50%",
      "la mitad de los días",
      "la mitad de las veces",
      "50% de los días",
      "duermo mal",
      "muchas veces estoy cansado",
      "muchas veces me siento cansado",
      "muchos días estoy cansado",
      "muchos días me siento cansado",
      "me suele faltar la energía",
      "suelo tener problemas",
      "tengo problemas",
      "tengo problemas de sueño",
      "tengo problemas de alimentación",
      "tengo problemas con la comida",
      "tengo dificultades",
      "suelo tener dificultades",
      "tengo dificultades de sueño",
      "tengo dificultades de alimentación",
      "tengo dificultades con la comida",
      "me llevo mal",
      "lo llevo mal",
      "llevo mal",
      "ocho días",
      "nueve días",
      "diez días",
      "once días",
      "doce días",
      "trece días",
      "catorce días",
      "8 días",
      "9 días",
      "10 días",
      "11 días",
      "12 días",
      "13 días",
      "14 días",
      "muchas veces estoy lento",
      "muchas veces me muevo lento",
      "muchas veces me muevo lentamente",
      "muchas veces estoy inquieto",
      "muchas veces estoy agitado",
      "muchas veces estoy nervioso",
      "muchas veces estoy lenta",
      "muchas veces me muevo lenta",
      "muchas veces estoy inquieta",
      "muchas veces estoy agitad",
      "muchas veces estoy agitada",
      "muchas veces estoy nerviosa",
      "muchas veces pienso en matarme",
      "muchas veces pienso en sucidarme",
      "muchas veces pienso en hacerme daño",
      "muchas veces pienso en quitarme la vida",
      "muchas veces pienso en cortarme las venas",
      "muchas veces pienso en tirarme por la ventana",
      "muchas veces pienso en tirarme de un puente",
      "muchos días"
    ]
  },
  {
    "value": "Puntos_3",
    "synonyms": [
      "Puntos_3",
      "casi todos los días",
      "todos los días",
      "siempre",
      "muchísumo",
      "muchas veces",
      "con mucha frecuencia",
      "mucha frecuencia",
      "más de la cuenta",
      "mayoría de los días",
      "a diario",
      "diariamente",
      "las 24 horas del día",
      "las 24h del día",
      "constantemente",
      "mucha",
      "todo el tiempo",
      "mucho",
      "continuamente",
      "mayoría de días",
      "sin parar",
      "mayoría de veces",
      "mayoría de las veces",
      "incesantemente",
      "sin descanso",
      "24h al día",
      "24 horas al día",
      "constante",
      "muchísimo",
      "todo me deprime",
      "siempre estoy deprimido",
      "siempre estoy deprimida",
      "siempre estoy decaído",
      "siempre estoy decaída",
      "nada de interés",
      "placer por nada",
      "placer en dada",
      "interés en nada",
      "interés por nada",
      "no tengo interés por nada",
      "duermo fatal",
      "no duermo nada",
      "duermo demasiado",
      "duermo muy mal",
      "estoy todo el día en la cama",
      "me paso el día durmiendo",
      "me paso el día en la cama",
      "no salgo de la cama",
      "yo nunca estoy cansado",
      "nunca me falta la energía",
      "siempre estoy cansado",
      "siempre me falta la energía",
      "estoy siempre agotado",
      "me siento agotado",
      "tengo muchos problemas",
      "tengo muchos problemas con la comida",
      "tengo muchos problemas con el sueño",
      "siempre tengo el problema",
      "siempre tengo dificultades",
      "tengo muchas dificultades",
      "me resulta muy complicado",
      "lo llevo muy mal",
      "me llevo muy mal",
      "siempre estoy lento",
      "siempre me muevo lento",
      "siempre me muevo lentamente",
      "siempre estoy inquieto",
      "siempre estoy agitado",
      "siempre estoy nervioso",
      "siempre estoy lenta",
      "siempre me muevo lenta",
      "siempre estoy inquieta",
      "siempre estoy agitada",
      "siempre estoy nerviosa",
      "15 días",
      "quice días",
      "quiero matarme",
      "quiero suicidarme",
      "pienso todo el rato en matarme",
      "pienso todo el rato en suicidarme",
      "pienso todo el rato en hacerme daño",
      "pienso todo el rato en quitarme la vida",
      "pienso constantemente en matarme",
      "pienso constantemente en quitarme la vida",
      "pienso constantemente en suicidarme",
      "pienso constantemente en hacerme daño",
      "cortarme las venas",
      "tirarme de un puente",
      "tirarme por la ventana",
      "pegarme un tiro",
      "no me interesa nada",
      "no tengo placer por nada",
      "no me da placer nada",
      "todo el rato"
    ]
  }
]